uv_easy/__init__.py
uv_easy/__main__.py
uv_easy/builder.py
uv_easy/changelog.py
uv_easy/cli.py
uv_easy/project.py
uv_easy/publisher.py
uv_easy/versioning.py
uv_easy/workflow.py
uv_easy-0.2.9.dist-info/METADATA
uv_easy-0.2.9.dist-info/WHEEL
uv_easy-0.2.9.dist-info/entry_points.txt
uv_easy-0.2.9.dist-info/RECORD
