Metadata-Version: 2.4
Name: uv-easy
Version: 0.2.9
Summary: uv를 더 쉽게 사용하기 위한 도구
Project-URL: Homepage, https://github.com/hakunamta00700/uv_easy
Project-URL: Repository, https://github.com/hakunamta00700/uv_easy
Project-URL: Issues, https://github.com/hakunamta00700/uv_easy/issues
Requires-Python: >=3.9
Requires-Dist: click>=8.0.0
Requires-Dist: toml>=0.10.0
Requires-Dist: twine>=6.2.0
